{
  "id": "spell:keyhole",
  "name": "Keyhole",
  "tags": ["spell", "transmutation", "arcanist", "arcanist1", "cleric", "cleric1", "oracle", "oracle1", "sorcerer", "sorcerer1", "warpriest", "warpriest1", "witch", "witch1", "wizard", "wizard1"],
  "prerequisiteFormula": "any(@class:arcanist\u003e\u003d1,@class:cleric\u003e\u003d1,@class:oracle\u003e\u003d1,@class:sorcerer\u003e\u003d1,@class:warpriest\u003e\u003d1,@class:witch\u003e\u003d1,@class:wizard\u003e\u003d1)",
  "description": {
    "text": "By touching a single door, gate, or other portal, you create a keyhole where none existed before or double the size of an existing keyhole. A conjured keyhole allows you to peer through the door, though the limited perspective imposes a –10 penalty on Perception checks to spot anything beyond. It also allows a sealed door to be locked or picked if it could not be before. Locking or unlocking such a door requires a successful Disable Device check with a DC equal to the barrier\u0027s break DC + 10. Enlarging an existing keyhole allows viewers to peer through to whatever lies beyond, even if the preexisting keyhole did not allow it, and it reduces the Disable Device DC to open or lock the door by 5."
  }
}