{
  "id": "spell:ascension",
  "name": "Ascension",
  "tags": ["sorcerer", "spell", "cleric", "oracle", "sorcerer9", "arcanist9", "cleric9", "druid", "druid9", "arcanist", "witch", "wizard9", "oracle9", "wizard", "witch9", "universal"],
  "prerequisiteFormula": "any(@class:arcanist\u003e\u003d18,@class:cleric\u003e\u003d15,@class:druid\u003e\u003d15,@class:oracle\u003e\u003d18,@class:sorcerer\u003e\u003d18,@class:witch\u003e\u003d15,@class:wizard\u003e\u003d15)",
  "description": {
    "text": "You imbue a number of creatures with mythic power, granting each of them 1st tier in a mythic path of its choice. The creatures immediately gain the benefits of their chosen paths. Divide the duration evenly among all targets."
  }
}