{
  "id": "class:skald#court_poet",
  "name": "Court Poet",
  "tags": ["archetype", "skald"],
  "enabledFormula": "!@modifies:ability:inspired_rage#skald AND !@modifies:ability:song_of_strength#skald AND !@modifies:ability:well_versed#skald",
  "maxStacks": 1,
  "description": {
  },
  "stacks": {
    "fixedStack": {
      "stacks": [{
        "effects": [{
          "setAction": {
            "targetKey": "modifies:ability:inspired_rage#skald",
            "numberValue": 1
          }
        }, {
          "setAction": {
            "targetKey": "modifies:ability:song_of_strength#skald",
            "numberValue": 1
          }
        }, {
          "setAction": {
            "targetKey": "modifies:ability:well_versed#skald",
            "numberValue": 1
          }
        }]
      }]
    }
  },
  "featureModifications": [{
    "targetFeatureId": "class:skald",
    "stackModifications": [{
      "targetStackCount": 1,
      "linksToAdd": ["ability:insightful_contemplation#skald_court_poet"]
    }, {
      "targetStackCount": 2,
      "linksToAdd": ["ability:handling_the_crowd#skald_court_poet"]
    }, {
      "targetStackCount": 6,
      "linksToAdd": ["ability:song_of_inspiration#skald_court_poet"]
    }]
  }]
}