{
  "id": "spell:windy_escape",
  "name": "Windy Escape",
  "tags": ["spell", "transmutation_air", "arcanist", "arcanist1", "bard", "bard1", "bloodrager", "bloodrager1", "druid", "druid1", "hunter", "hunter1", "magus", "magus1", "skald", "skald1", "sorcerer", "sorcerer1"],
  "prerequisiteFormula": "any(@class:arcanist\u003e\u003d1,@class:bard\u003e\u003d1,@class:bloodrager\u003e\u003d4,@class:druid\u003e\u003d1,@class:hunter\u003e\u003d1,@class:magus\u003e\u003d1,@class:skald\u003e\u003d1,@class:sorcerer\u003e\u003d1)",
  "description": {
    "text": "You respond to an attack by briefly becoming vaporous and insubstantial, allowing the attack to pass harmlessly through you. You gain DR 10/magic against this attack and are immune to any poison, sneak attacks, or critical hit effect from that attack."
  }
}