{
  "id": "spell:glimpse_the_hidden",
  "name": "Glimpse the Hidden",
  "tags": ["sorcerer", "spell", "alchemist", "divination", "arcanist3", "investigator3", "investigator", "inquisitor3", "inquisitor", "sorcerer3", "arcanist", "summoner", "wizard", "alchemist3", "summoner3", "wizard3"],
  "prerequisiteFormula": "any(@class:alchemist\u003e\u003d7,@class:arcanist\u003e\u003d6,@class:inquisitor\u003e\u003d7,@class:investigator\u003e\u003d7,@class:sorcerer\u003e\u003d6,@class:summoner\u003e\u003d7,@class:wizard\u003e\u003d3)",
  "description": {
    "text": "This spell functions as see invisibility, except as noted here. This spell cannot be made permanent."
  }
}