{
  "id": "spell:sure_casting",
  "name": "Sure Casting",
  "tags": ["sorcerer", "spell", "cleric", "divination", "oracle", "arcanist1", "witch1", "skald", "sorcerer1", "wizard1", "bard1", "oracle1", "inquisitor1", "inquisitor", "arcanist", "cleric1", "warpriest", "witch", "wizard", "warpriest1", "skald1", "bard"],
  "prerequisiteFormula": "any(@class:arcanist\u003e\u003d1,@class:bard\u003e\u003d1,@class:cleric\u003e\u003d1,@class:inquisitor\u003e\u003d1,@class:oracle\u003e\u003d1,@class:skald\u003e\u003d1,@class:sorcerer\u003e\u003d1,@class:warpriest\u003e\u003d1,@class:witch\u003e\u003d1,@class:wizard\u003e\u003d1)",
  "description": {
    "text": "You gain temporary insight into your enemies\u0027 magical defenses. When you next cast a spell before the end of the next round, treat your caster level as 5 higher than normal for the purpose of overcoming spell resistance. This bonus doesn\u0027t increase any other effects that depend on caster level, such as the spell\u0027s damage or range, and affects only the first spell cast after sure casting."
  }
}