{
  "id": 111101059,
  "name": "Courtier\u0027s Outfit",
  "tags": ["item", "mundane", "slotless"],
  "cost": 30.0,
  "weight": 6.0,
  "description": {
    "text": "This outfit includes tailored clothes in whatever fashion happens to be current in noble courts of that region. Anyone trying to influence nobles or courtiers while wearing street dress will have a hard time of it (–2 penalty on Charisma-based skill checks to influence such individuals). If you wear this outfit without jewelry (costing an additional 50 gp), you look like an out-of-place commoner."
  }
}