{
  "id": "spell:shadow_projection",
  "name": "Shadow Projection",
  "tags": ["arcanist4", "sorcerer4", "spell", "spell", "wizard4"],
  "description": {
    "text": "With this spell, you infuse your life force and psyche into your shadow, giving it independent life and movement as if it were an undead shadow (see Pathfinder RPG Bestiary245). Your physical body lies comatose while you are projecting your shadow, and your body has no shadow or reflection while the spell is in effect.",
    "sections": {
      "Components": "S",
      "School": "necromancy [evil]",
      "Casting Time": "1 minute",
      "Targets": "you",
      "Duration": "1 hour/level (D)",
      "Range": "personal"
    }
  },
  "stacks": {
    "repeatingStack": {
    }
  }
}