{
  "id": 111375,
  "name": "Lamentation Of The Faithless",
  "tags": ["item", "weapon", "slotless"],
  "optionSets": [1111043],
  "weight": 8.0,
  "description": {
    "text": "Szuriel\u0027s weapon is Lamentation of the Faithless, a black-bladed +5 speed unholy greatsword. When using the blade to attack, Szuriel regains 1d6 hit points with each successful hit. If Szuriel presents her sword as a standard action, all creatures within 60 feet that view it are blinded and affected by crushing despair for 1d4+1 rounds unless they succeed at a DC 30 Will save. Creatures with the good subtype and divine spellcasters take a –4 penalty on this save. As a standard action, Szuriel can call the sword to her hand from any distance, including across planar boundaries.",
    "sections": {
      "Destruction": "The sword shatters and sublimates if it is ever placed in the empty, walled garden at the summit of Heaven\u0027s mountain by a risen, repentant fiend."
    }
  },
  "actions": ["Attack"],
  "stats": {
    "type:two-handed": 1,
    "crit_multiplier": 2,
    "crit_range": 19,
    "dice_count": 2,
    "dice_sides": 6
  },
  "attacks": [{
    "name": "Attack #1",
    "condition": "@bab \u003e 0",
    "chanceToHit": {
      "value": "1d20 + (@bab-0) + @str_mod + @size_mod",
      "toBeat": "@target:ac"
    },
    "hitDamage": "2d6",
    "missDamage": "0"
  }, {
    "name": "Attack #2",
    "condition": "@bab \u003e 5",
    "chanceToHit": {
      "value": "1d20 + (@bab-5) + @str_mod + @size_mod",
      "toBeat": "@target:ac"
    },
    "hitDamage": "2d6",
    "missDamage": "0"
  }, {
    "name": "Attack #3",
    "condition": "@bab \u003e 10",
    "chanceToHit": {
      "value": "1d20 + (@bab-10) + @str_mod + @size_mod",
      "toBeat": "@target:ac"
    },
    "hitDamage": "2d6",
    "missDamage": "0"
  }, {
    "name": "Attack #4",
    "condition": "@bab \u003e 15",
    "chanceToHit": {
      "value": "1d20 + (@bab-15) + @str_mod + @size_mod",
      "toBeat": "@target:ac"
    },
    "hitDamage": "2d6",
    "missDamage": "0"
  }, {
    "name": "Attack #5",
    "condition": "@bab \u003e 20",
    "chanceToHit": {
      "value": "1d20 + (@bab-20) + @str_mod + @size_mod",
      "toBeat": "@target:ac"
    },
    "hitDamage": "2d6",
    "missDamage": "0"
  }]
}