{
  "id": "slayer_talent:rogue_advanced_talent_troupe_teamwork",
  "name": "Rogue Advanced Talent (Troupe Teamwork)",
  "tags": ["class_feature", "slayer", "slayer_talent"],
  "enabledFormula": "@ability:advanced_talents#slayer",
  "maxStacks": 1,
  "description": {
    "sections": {
      "Benefit": "You treat any ally that is also flanking an opponent you are flanking as though the ally were adjacent to you for the purpose of determining whether you receive the benefits of your allies teamwork feats."
    }
  },
  "stacks": {
    "fixedStack": {
    }
  }
}