{
  "id": "magus_arcana:arcane_edge",
  "name": "Arcane Edge",
  "tags": ["class_feature", "magus", "magus_arcana"],
  "enabledFormula": "@class:magus\u003e\u003d9",
  "maxStacks": 1,
  "description": {
    "text": "Use your arcane pool to do bleed damage",
    "sections": {
      "Benefit": "The magus can expend 1 point from his arcane pool as an immediate action after hitting a target with a slashing or piercing weapon in order to deal an amount of bleed damage equal to his Intelligence modifier (minimum 0)."
    }
  },
  "stacks": {
    "fixedStack": {
    }
  }
}