{
  "id": "class:investigator#engineer_investigator_archetype",
  "name": "Engineer (Investigator Archetype)",
  "tags": ["investigator", "archetype"],
  "description": {
  },
  "template": {
    "id": "class:investigator#engineer_investigator_archetype",
    "sections": [{
      "condition": "@class:investigator\u003e\u003d1",
      "effects": [{
        "targetKey": "ability:the_trapfinding_poison_lore_and_poison_resistance_class_features#investigator",
        "renameAction": {
          "renamedKey": "ability:custom_mechanism#investigator_engineer_investigator_archetype"
        }
      }, {
        "targetKey": "ability:trap_sense#investigator",
        "renameAction": {
          "renamedKey": "ability:mechanical_understanding#investigator_engineer_investigator_archetype"
        }
      }]
    }, {
      "condition": "@class:investigator\u003e\u003d2",
      "effects": [{
        "targetKey": "ability:the_trapfinding_poison_lore_and_poison_resistance_class_features#investigator",
        "renameAction": {
          "renamedKey": "ability:custom_mechanism#investigator_engineer_investigator_archetype"
        }
      }, {
        "targetKey": "ability:trap_sense#investigator",
        "renameAction": {
          "renamedKey": "ability:mechanical_understanding#investigator_engineer_investigator_archetype"
        }
      }]
    }, {
      "condition": "@class:investigator\u003e\u003d3",
      "effects": [{
        "targetKey": "ability:the_trapfinding_poison_lore_and_poison_resistance_class_features#investigator",
        "renameAction": {
          "renamedKey": "ability:custom_mechanism#investigator_engineer_investigator_archetype"
        }
      }, {
        "targetKey": "ability:trap_sense#investigator",
        "renameAction": {
          "renamedKey": "ability:mechanical_understanding#investigator_engineer_investigator_archetype"
        }
      }]
    }, {
      "condition": "@class:investigator\u003e\u003d4",
      "effects": [{
        "targetKey": "ability:the_trapfinding_poison_lore_and_poison_resistance_class_features#investigator",
        "renameAction": {
          "renamedKey": "ability:custom_mechanism#investigator_engineer_investigator_archetype"
        }
      }, {
        "targetKey": "ability:trap_sense#investigator",
        "renameAction": {
          "renamedKey": "ability:mechanical_understanding#investigator_engineer_investigator_archetype"
        }
      }]
    }, {
      "condition": "@class:investigator\u003e\u003d5",
      "effects": [{
        "targetKey": "ability:the_trapfinding_poison_lore_and_poison_resistance_class_features#investigator",
        "renameAction": {
          "renamedKey": "ability:custom_mechanism#investigator_engineer_investigator_archetype"
        }
      }, {
        "targetKey": "ability:trap_sense#investigator",
        "renameAction": {
          "renamedKey": "ability:mechanical_understanding#investigator_engineer_investigator_archetype"
        }
      }]
    }, {
      "condition": "@class:investigator\u003e\u003d6",
      "effects": [{
        "targetKey": "ability:the_trapfinding_poison_lore_and_poison_resistance_class_features#investigator",
        "renameAction": {
          "renamedKey": "ability:custom_mechanism#investigator_engineer_investigator_archetype"
        }
      }, {
        "targetKey": "ability:trap_sense#investigator",
        "renameAction": {
          "renamedKey": "ability:mechanical_understanding#investigator_engineer_investigator_archetype"
        }
      }]
    }, {
      "condition": "@class:investigator\u003e\u003d7",
      "effects": [{
        "targetKey": "ability:the_trapfinding_poison_lore_and_poison_resistance_class_features#investigator",
        "renameAction": {
          "renamedKey": "ability:custom_mechanism#investigator_engineer_investigator_archetype"
        }
      }, {
        "targetKey": "ability:trap_sense#investigator",
        "renameAction": {
          "renamedKey": "ability:mechanical_understanding#investigator_engineer_investigator_archetype"
        }
      }]
    }, {
      "condition": "@class:investigator\u003e\u003d8",
      "effects": [{
        "targetKey": "ability:the_trapfinding_poison_lore_and_poison_resistance_class_features#investigator",
        "renameAction": {
          "renamedKey": "ability:custom_mechanism#investigator_engineer_investigator_archetype"
        }
      }, {
        "targetKey": "ability:trap_sense#investigator",
        "renameAction": {
          "renamedKey": "ability:mechanical_understanding#investigator_engineer_investigator_archetype"
        }
      }]
    }, {
      "condition": "@class:investigator\u003e\u003d9",
      "effects": [{
        "targetKey": "ability:the_trapfinding_poison_lore_and_poison_resistance_class_features#investigator",
        "renameAction": {
          "renamedKey": "ability:custom_mechanism#investigator_engineer_investigator_archetype"
        }
      }, {
        "targetKey": "ability:trap_sense#investigator",
        "renameAction": {
          "renamedKey": "ability:mechanical_understanding#investigator_engineer_investigator_archetype"
        }
      }]
    }, {
      "condition": "@class:investigator\u003e\u003d10",
      "effects": [{
        "targetKey": "ability:the_trapfinding_poison_lore_and_poison_resistance_class_features#investigator",
        "renameAction": {
          "renamedKey": "ability:custom_mechanism#investigator_engineer_investigator_archetype"
        }
      }, {
        "targetKey": "ability:trap_sense#investigator",
        "renameAction": {
          "renamedKey": "ability:mechanical_understanding#investigator_engineer_investigator_archetype"
        }
      }]
    }, {
      "condition": "@class:investigator\u003e\u003d11",
      "effects": [{
        "targetKey": "ability:the_trapfinding_poison_lore_and_poison_resistance_class_features#investigator",
        "renameAction": {
          "renamedKey": "ability:custom_mechanism#investigator_engineer_investigator_archetype"
        }
      }, {
        "targetKey": "ability:trap_sense#investigator",
        "renameAction": {
          "renamedKey": "ability:mechanical_understanding#investigator_engineer_investigator_archetype"
        }
      }]
    }, {
      "condition": "@class:investigator\u003e\u003d12",
      "effects": [{
        "targetKey": "ability:the_trapfinding_poison_lore_and_poison_resistance_class_features#investigator",
        "renameAction": {
          "renamedKey": "ability:custom_mechanism#investigator_engineer_investigator_archetype"
        }
      }, {
        "targetKey": "ability:trap_sense#investigator",
        "renameAction": {
          "renamedKey": "ability:mechanical_understanding#investigator_engineer_investigator_archetype"
        }
      }]
    }, {
      "condition": "@class:investigator\u003e\u003d13",
      "effects": [{
        "targetKey": "ability:the_trapfinding_poison_lore_and_poison_resistance_class_features#investigator",
        "renameAction": {
          "renamedKey": "ability:custom_mechanism#investigator_engineer_investigator_archetype"
        }
      }, {
        "targetKey": "ability:trap_sense#investigator",
        "renameAction": {
          "renamedKey": "ability:mechanical_understanding#investigator_engineer_investigator_archetype"
        }
      }]
    }, {
      "condition": "@class:investigator\u003e\u003d14",
      "effects": [{
        "targetKey": "ability:the_trapfinding_poison_lore_and_poison_resistance_class_features#investigator",
        "renameAction": {
          "renamedKey": "ability:custom_mechanism#investigator_engineer_investigator_archetype"
        }
      }, {
        "targetKey": "ability:trap_sense#investigator",
        "renameAction": {
          "renamedKey": "ability:mechanical_understanding#investigator_engineer_investigator_archetype"
        }
      }]
    }, {
      "condition": "@class:investigator\u003e\u003d15",
      "effects": [{
        "targetKey": "ability:the_trapfinding_poison_lore_and_poison_resistance_class_features#investigator",
        "renameAction": {
          "renamedKey": "ability:custom_mechanism#investigator_engineer_investigator_archetype"
        }
      }, {
        "targetKey": "ability:trap_sense#investigator",
        "renameAction": {
          "renamedKey": "ability:mechanical_understanding#investigator_engineer_investigator_archetype"
        }
      }]
    }, {
      "condition": "@class:investigator\u003e\u003d16",
      "effects": [{
        "targetKey": "ability:the_trapfinding_poison_lore_and_poison_resistance_class_features#investigator",
        "renameAction": {
          "renamedKey": "ability:custom_mechanism#investigator_engineer_investigator_archetype"
        }
      }, {
        "targetKey": "ability:trap_sense#investigator",
        "renameAction": {
          "renamedKey": "ability:mechanical_understanding#investigator_engineer_investigator_archetype"
        }
      }]
    }, {
      "condition": "@class:investigator\u003e\u003d17",
      "effects": [{
        "targetKey": "ability:the_trapfinding_poison_lore_and_poison_resistance_class_features#investigator",
        "renameAction": {
          "renamedKey": "ability:custom_mechanism#investigator_engineer_investigator_archetype"
        }
      }, {
        "targetKey": "ability:trap_sense#investigator",
        "renameAction": {
          "renamedKey": "ability:mechanical_understanding#investigator_engineer_investigator_archetype"
        }
      }]
    }, {
      "condition": "@class:investigator\u003e\u003d18",
      "effects": [{
        "targetKey": "ability:the_trapfinding_poison_lore_and_poison_resistance_class_features#investigator",
        "renameAction": {
          "renamedKey": "ability:custom_mechanism#investigator_engineer_investigator_archetype"
        }
      }, {
        "targetKey": "ability:trap_sense#investigator",
        "renameAction": {
          "renamedKey": "ability:mechanical_understanding#investigator_engineer_investigator_archetype"
        }
      }]
    }, {
      "condition": "@class:investigator\u003e\u003d19",
      "effects": [{
        "targetKey": "ability:the_trapfinding_poison_lore_and_poison_resistance_class_features#investigator",
        "renameAction": {
          "renamedKey": "ability:custom_mechanism#investigator_engineer_investigator_archetype"
        }
      }, {
        "targetKey": "ability:trap_sense#investigator",
        "renameAction": {
          "renamedKey": "ability:mechanical_understanding#investigator_engineer_investigator_archetype"
        }
      }]
    }, {
      "condition": "@class:investigator\u003e\u003d20",
      "effects": [{
        "targetKey": "ability:the_trapfinding_poison_lore_and_poison_resistance_class_features#investigator",
        "renameAction": {
          "renamedKey": "ability:custom_mechanism#investigator_engineer_investigator_archetype"
        }
      }, {
        "targetKey": "ability:trap_sense#investigator",
        "renameAction": {
          "renamedKey": "ability:mechanical_understanding#investigator_engineer_investigator_archetype"
        }
      }]
    }]
  }
}