{
  "id": "spell:catatonia",
  "name": "Catatonia",
  "tags": ["alchemist2", "arcanist3", "bard2", "cleric3", "investigator2", "oracle3", "skald2", "sorcerer3", "spell", "spell", "warpriest3", "witch3", "wizard3"],
  "description": {
    "text": "You touch the target and place it into a deathlike state that persists for the duration. The target appears to be dead, and any creature that interacts with the target must succeed at a DC 20 Heal check to recognize it is actually alive.",
    "sections": {
      "Components": "S",
      "School": "necromancy",
      "Spell Resistance": "yes",
      "Casting Time": "1 standard action",
      "Targets": "willing creature touched",
      "Duration": "1 hour/level (D)",
      "Saving Throw": "none",
      "Range": "touch"
    }
  },
  "stacks": {
    "repeatingStack": {
    }
  }
}