{
  "id": "spell:alter_self",
  "name": "Alter Self",
  "type": "ABILITY_TYPE_SP",
  "school": "transmutation",
  "range": {
    "category": "PERSONAL"
  },
  "targets": "you",
  "duration": "1 min./level",
  "description": "When you cast this spell, you can assume the form of any Small or Medium creature of the humanoid type. If the form you assume has any of the following abilities, you gain the listed ability: darkvision 60 feet, low-light vision, scent, and swim 30 feet. Small creature: If the form you take is that of a Small humanoid, you gain a +2 size bonus to your Dexterity. Medium creature: If the form you take is that of a Medium humanoid, you gain a +2 size bonus to your Strength.",
  "level": [{
    "classId": "class:bard_2_sorcerer",
    "level": 2
  }, {
    "classId": "class:wizard_2_witch_2_summoner",
    "level": 2
  }, {
    "classId": "class:unchained_summoner_2_alchemist_2_magus_2_shaman_2_psychic_2_mesmerist_2_medium",
    "level": 2
  }, {
    "classId": "class:bard_2_sorcerer",
    "level": 2
  }, {
    "classId": "class:wizard_2_witch_2_summoner",
    "level": 2
  }, {
    "classId": "class:unchained_summoner_2_alchemist_2_magus_2_shaman_2_psychic_2_mesmerist_2_medium",
    "level": 2
  }, {
    "classId": "class:bard_2_sorcerer",
    "level": 2
  }, {
    "classId": "class:wizard_2_witch_2_summoner",
    "level": 2
  }, {
    "classId": "class:unchained_summoner_2_alchemist_2_magus_2_shaman_2_psychic_2_mesmerist_2_medium",
    "level": 2
  }, {
    "classId": "class:bard_2_sorcerer",
    "level": 2
  }, {
    "classId": "class:wizard_2_witch_2_summoner",
    "level": 2
  }, {
    "classId": "class:unchained_summoner_2_alchemist_2_magus_2_shaman_2_psychic_2_mesmerist_2_medium",
    "level": 2
  }, {
    "classId": "class:bard_2_sorcerer",
    "level": 2
  }, {
    "classId": "class:wizard_2_witch_2_summoner",
    "level": 2
  }, {
    "classId": "class:unchained_summoner_2_alchemist_2_magus_2_shaman_2_psychic_2_mesmerist_2_medium",
    "level": 2
  }, {
    "classId": "class:bard_2_sorcerer",
    "level": 2
  }, {
    "classId": "class:wizard_2_witch_2_summoner",
    "level": 2
  }, {
    "classId": "class:unchained_summoner_2_alchemist_2_magus_2_shaman_2_psychic_2_mesmerist_2_medium",
    "level": 2
  }, {
    "classId": "class:bard_2_sorcerer",
    "level": 2
  }, {
    "classId": "class:wizard_2_witch_2_summoner",
    "level": 2
  }, {
    "classId": "class:unchained_summoner_2_alchemist_2_magus_2_shaman_2_psychic_2_mesmerist_2_medium",
    "level": 2
  }, {
    "classId": "class:bard_2_sorcerer",
    "level": 2
  }, {
    "classId": "class:wizard_2_witch_2_summoner",
    "level": 2
  }, {
    "classId": "class:unchained_summoner_2_alchemist_2_magus_2_shaman_2_psychic_2_mesmerist_2_medium",
    "level": 2
  }, {
    "classId": "class:bard_2_sorcerer",
    "level": 2
  }, {
    "classId": "class:wizard_2_witch_2_summoner",
    "level": 2
  }, {
    "classId": "class:unchained_summoner_2_alchemist_2_magus_2_shaman_2_psychic_2_mesmerist_2_medium",
    "level": 2
  }, {
    "classId": "class:bard_2_sorcerer",
    "level": 2
  }, {
    "classId": "class:wizard_2_witch_2_summoner",
    "level": 2
  }, {
    "classId": "class:unchained_summoner_2_alchemist_2_magus_2_shaman_2_psychic_2_mesmerist_2_medium",
    "level": 2
  }]
}