{
  "id": "spell:remove_sickness",
  "name": "Remove Sickness",
  "type": "ABILITY_TYPE_SP",
  "school": "conjuration",
  "range": {
    "category": "CLOSE"
  },
  "targets": "one creature",
  "duration": "10 minutes/level; see text",
  "description": "You quell feelings of illness and nausea in the target, giving it a +4 morale bonus on saving throws against disease, nausea, and sickened effects. If the subject is already under the influence of one of these effects when receiving the spell, that effect is suppressed for the duration of the spell.",
  "level": [{
    "classId": "class:cleric",
    "level": 1
  }, {
    "classId": "class:oracle_1_druid_1_witch_1_mesmerist_1_spiritualist",
    "level": 1
  }, {
    "classId": "class:cleric",
    "level": 1
  }, {
    "classId": "class:oracle_1_druid_1_witch_1_mesmerist_1_spiritualist",
    "level": 1
  }, {
    "classId": "class:cleric",
    "level": 1
  }, {
    "classId": "class:oracle_1_druid_1_witch_1_mesmerist_1_spiritualist",
    "level": 1
  }, {
    "classId": "class:cleric",
    "level": 1
  }, {
    "classId": "class:oracle_1_druid_1_witch_1_mesmerist_1_spiritualist",
    "level": 1
  }, {
    "classId": "class:cleric",
    "level": 1
  }, {
    "classId": "class:oracle_1_druid_1_witch_1_mesmerist_1_spiritualist",
    "level": 1
  }]
}