{
  "id": 11110917,
  "name": "Potion Of Call Lightning",
  "tags": ["item", "potion", "none"],
  "cost": 750.0,
  "description": {
    "text": "Immediately upon completion of the spell, and once per round thereafter, you may call down a 5-foot-wide, 30-foot-long, vertical bolt of lightning that deals 3d6 points of electricity damage. The bolt of lightning flashes down in a vertical stroke at whatever target point you choose within the spell\u0027s range (measured from your position at the time). Any creature in the target square or in the path of the bolt is affected."
  }
}