{
  "id": "spell:silent_image",
  "name": "Silent Image",
  "tags": ["arcanist1", "bard1", "magus1", "skald1", "sorcerer1", "spell", "spell", "wizard1"],
  "description": {
    "text": "This spell creates the visual illusion of an object, creature, or force, as visualized by you. The illusion does not create sound, smell, texture, or temperature. You can move the image within the limits of the size of the effect.",
    "sections": {
      "Components": "V, S, F (a bit of fleece)",
      "School": "illusion (figment)",
      "Spell Resistance": "no",
      "Casting Time": "1 standard action",
      "Duration": "concentration",
      "Saving Throw": "Will disbelief (if interacted with)",
      "Range": "long (400 ft. + 40 ft./level)"
    }
  },
  "stacks": {
    "repeatingStack": {
    }
  }
}